mpong/__init__.py
mpong/mpong.py
mpong-0.0.8.dist-info/LICENSE
mpong-0.0.8.dist-info/METADATA
mpong-0.0.8.dist-info/WHEEL
mpong-0.0.8.dist-info/entry_points.txt
mpong-0.0.8.dist-info/top_level.txt
mpong-0.0.8.dist-info/RECORD
