Metadata-Version: 2.1
Name: mpong
Version: 0.0.8
Summary: A simple pong game in Python
Home-page: https://github.com/manorajesh/mpong
Author: Me
Author-email: shapely_indexes0d@icloud.com
Project-URL: Bug Tracker, https://github.com/manorajesh/mpong/issues
Classifier: Programming Language :: Python :: 3
Classifier: License :: OSI Approved :: Apache Software License
Classifier: Operating System :: OS Independent
Requires-Python: >=3.6
License-File: LICENSE
Requires-Dist: readchar (>=3.0.5)
